terml/__init__.py
terml/__main__.py
terml/ansi_colors.py
terml/cli.py
terml/formatter.py
terml/parser.py
terml-0.1.0.dist-info/LICENSE
terml-0.1.0.dist-info/METADATA
terml-0.1.0.dist-info/WHEEL
terml-0.1.0.dist-info/entry_points.txt
terml-0.1.0.dist-info/RECORD
