Metadata-Version: 2.1
Name: terml
Version: 0.1.0
Summary: Terminal Markup Language based on BBCode
Home-page: https://github.com/s3rgeym/terml
License: MIT
Author: Sergey M
Requires-Python: >=3.11,<4.0
Classifier: License :: OSI Approved :: MIT License
Classifier: Programming Language :: Python :: 3
Classifier: Programming Language :: Python :: 3.11
Project-URL: Repository, https://github.com/s3rgeym/terml
